ablina/__init__.py
ablina/experimental.py
ablina/field.py
ablina/form.py
ablina/linearmap.py
ablina/mathset.py
ablina/matrix.py
ablina/operations.py
ablina/parser.py
ablina/utils.py
ablina/vectorspace.py
ablina/visualize.py
ablina/vs_utils.py
ablina-0.4.3.dist-info/licenses/LICENSE
ablina-0.4.3.dist-info/METADATA
ablina-0.4.3.dist-info/WHEEL
ablina-0.4.3.dist-info/top_level.txt
ablina-0.4.3.dist-info/RECORD
